{
  "node": {
    "402351304280ad803702918ca0fe57280b42eb67": {
      "workers": {
        "app/page": "(action-browser)/./node_modules/next/dist/build/webpack/loaders/next-flight-action-entry-loader.js?actions=%5B%5B%22G%3A%5C%5CProjects%5C%5CDigiBeat%5C%5Csrc%5C%5Capp%5C%5Cactions%5C%5Ctiktok.ts%22%2C%5B%22fetchDailyVideoBreakdown%22%2C%22fetchVideos%22%2C%22deleteAccountGroup%22%2C%22fetchSnapshots%22%2C%22upsertVideo%22%2C%22fetchAccounts%22%2C%22triggerSync%22%2C%22fetchAccountGroups%22%2C%22upsertAccount%22%2C%22updateGroupMembers%22%2C%22createAccountGroup%22%5D%5D%5D&__client_imported__=true!"
      },
      "layer": {
        "app/page": "action-browser"
      }
    },
    "6f55f524f835e4d67c975ffa8506f6dcbcd5dc26": {
      "workers": {
        "app/page": "(action-browser)/./node_modules/next/dist/build/webpack/loaders/next-flight-action-entry-loader.js?actions=%5B%5B%22G%3A%5C%5CProjects%5C%5CDigiBeat%5C%5Csrc%5C%5Capp%5C%5Cactions%5C%5Ctiktok.ts%22%2C%5B%22fetchDailyVideoBreakdown%22%2C%22fetchVideos%22%2C%22deleteAccountGroup%22%2C%22fetchSnapshots%22%2C%22upsertVideo%22%2C%22fetchAccounts%22%2C%22triggerSync%22%2C%22fetchAccountGroups%22%2C%22upsertAccount%22%2C%22updateGroupMembers%22%2C%22createAccountGroup%22%5D%5D%5D&__client_imported__=true!"
      },
      "layer": {
        "app/page": "action-browser"
      }
    },
    "744ac6272c1421108303e99710c1d60810045b91": {
      "workers": {
        "app/page": "(action-browser)/./node_modules/next/dist/build/webpack/loaders/next-flight-action-entry-loader.js?actions=%5B%5B%22G%3A%5C%5CProjects%5C%5CDigiBeat%5C%5Csrc%5C%5Capp%5C%5Cactions%5C%5Ctiktok.ts%22%2C%5B%22fetchDailyVideoBreakdown%22%2C%22fetchVideos%22%2C%22deleteAccountGroup%22%2C%22fetchSnapshots%22%2C%22upsertVideo%22%2C%22fetchAccounts%22%2C%22triggerSync%22%2C%22fetchAccountGroups%22%2C%22upsertAccount%22%2C%22updateGroupMembers%22%2C%22createAccountGroup%22%5D%5D%5D&__client_imported__=true!"
      },
      "layer": {
        "app/page": "action-browser"
      }
    },
    "81f22211fa84bcdd2c67a66356e0d44e7dc6b531": {
      "workers": {
        "app/page": "(action-browser)/./node_modules/next/dist/build/webpack/loaders/next-flight-action-entry-loader.js?actions=%5B%5B%22G%3A%5C%5CProjects%5C%5CDigiBeat%5C%5Csrc%5C%5Capp%5C%5Cactions%5C%5Ctiktok.ts%22%2C%5B%22fetchDailyVideoBreakdown%22%2C%22fetchVideos%22%2C%22deleteAccountGroup%22%2C%22fetchSnapshots%22%2C%22upsertVideo%22%2C%22fetchAccounts%22%2C%22triggerSync%22%2C%22fetchAccountGroups%22%2C%22upsertAccount%22%2C%22updateGroupMembers%22%2C%22createAccountGroup%22%5D%5D%5D&__client_imported__=true!"
      },
      "layer": {
        "app/page": "action-browser"
      }
    },
    "85fead08dbe93a9eacf6c37c330d81e9b066b348": {
      "workers": {
        "app/page": "(action-browser)/./node_modules/next/dist/build/webpack/loaders/next-flight-action-entry-loader.js?actions=%5B%5B%22G%3A%5C%5CProjects%5C%5CDigiBeat%5C%5Csrc%5C%5Capp%5C%5Cactions%5C%5Ctiktok.ts%22%2C%5B%22fetchDailyVideoBreakdown%22%2C%22fetchVideos%22%2C%22deleteAccountGroup%22%2C%22fetchSnapshots%22%2C%22upsertVideo%22%2C%22fetchAccounts%22%2C%22triggerSync%22%2C%22fetchAccountGroups%22%2C%22upsertAccount%22%2C%22updateGroupMembers%22%2C%22createAccountGroup%22%5D%5D%5D&__client_imported__=true!"
      },
      "layer": {
        "app/page": "action-browser"
      }
    },
    "9219ea2b2cea1128bc0bff1ef0b94fda9d50ad42": {
      "workers": {
        "app/page": "(action-browser)/./node_modules/next/dist/build/webpack/loaders/next-flight-action-entry-loader.js?actions=%5B%5B%22G%3A%5C%5CProjects%5C%5CDigiBeat%5C%5Csrc%5C%5Capp%5C%5Cactions%5C%5Ctiktok.ts%22%2C%5B%22fetchDailyVideoBreakdown%22%2C%22fetchVideos%22%2C%22deleteAccountGroup%22%2C%22fetchSnapshots%22%2C%22upsertVideo%22%2C%22fetchAccounts%22%2C%22triggerSync%22%2C%22fetchAccountGroups%22%2C%22upsertAccount%22%2C%22updateGroupMembers%22%2C%22createAccountGroup%22%5D%5D%5D&__client_imported__=true!"
      },
      "layer": {
        "app/page": "action-browser"
      }
    },
    "a6504655bc7204509ac2a84aebbca42cd731f67d": {
      "workers": {
        "app/page": "(action-browser)/./node_modules/next/dist/build/webpack/loaders/next-flight-action-entry-loader.js?actions=%5B%5B%22G%3A%5C%5CProjects%5C%5CDigiBeat%5C%5Csrc%5C%5Capp%5C%5Cactions%5C%5Ctiktok.ts%22%2C%5B%22fetchDailyVideoBreakdown%22%2C%22fetchVideos%22%2C%22deleteAccountGroup%22%2C%22fetchSnapshots%22%2C%22upsertVideo%22%2C%22fetchAccounts%22%2C%22triggerSync%22%2C%22fetchAccountGroups%22%2C%22upsertAccount%22%2C%22updateGroupMembers%22%2C%22createAccountGroup%22%5D%5D%5D&__client_imported__=true!"
      },
      "layer": {
        "app/page": "action-browser"
      }
    },
    "a6686b75885c0c6fba5404716d34027f7cc5572e": {
      "workers": {
        "app/page": "(action-browser)/./node_modules/next/dist/build/webpack/loaders/next-flight-action-entry-loader.js?actions=%5B%5B%22G%3A%5C%5CProjects%5C%5CDigiBeat%5C%5Csrc%5C%5Capp%5C%5Cactions%5C%5Ctiktok.ts%22%2C%5B%22fetchDailyVideoBreakdown%22%2C%22fetchVideos%22%2C%22deleteAccountGroup%22%2C%22fetchSnapshots%22%2C%22upsertVideo%22%2C%22fetchAccounts%22%2C%22triggerSync%22%2C%22fetchAccountGroups%22%2C%22upsertAccount%22%2C%22updateGroupMembers%22%2C%22createAccountGroup%22%5D%5D%5D&__client_imported__=true!"
      },
      "layer": {
        "app/page": "action-browser"
      }
    },
    "c270e7cfb723aecfc54376bf4afdceec1eb84f86": {
      "workers": {
        "app/page": "(action-browser)/./node_modules/next/dist/build/webpack/loaders/next-flight-action-entry-loader.js?actions=%5B%5B%22G%3A%5C%5CProjects%5C%5CDigiBeat%5C%5Csrc%5C%5Capp%5C%5Cactions%5C%5Ctiktok.ts%22%2C%5B%22fetchDailyVideoBreakdown%22%2C%22fetchVideos%22%2C%22deleteAccountGroup%22%2C%22fetchSnapshots%22%2C%22upsertVideo%22%2C%22fetchAccounts%22%2C%22triggerSync%22%2C%22fetchAccountGroups%22%2C%22upsertAccount%22%2C%22updateGroupMembers%22%2C%22createAccountGroup%22%5D%5D%5D&__client_imported__=true!"
      },
      "layer": {
        "app/page": "action-browser"
      }
    },
    "cc048a21d4319d52c6956955d6b7419a0c0888b4": {
      "workers": {
        "app/page": "(action-browser)/./node_modules/next/dist/build/webpack/loaders/next-flight-action-entry-loader.js?actions=%5B%5B%22G%3A%5C%5CProjects%5C%5CDigiBeat%5C%5Csrc%5C%5Capp%5C%5Cactions%5C%5Ctiktok.ts%22%2C%5B%22fetchDailyVideoBreakdown%22%2C%22fetchVideos%22%2C%22deleteAccountGroup%22%2C%22fetchSnapshots%22%2C%22upsertVideo%22%2C%22fetchAccounts%22%2C%22triggerSync%22%2C%22fetchAccountGroups%22%2C%22upsertAccount%22%2C%22updateGroupMembers%22%2C%22createAccountGroup%22%5D%5D%5D&__client_imported__=true!"
      },
      "layer": {
        "app/page": "action-browser"
      }
    },
    "e013557a414f5aa88c094e25f715fa2dafe32a2f": {
      "workers": {
        "app/page": "(action-browser)/./node_modules/next/dist/build/webpack/loaders/next-flight-action-entry-loader.js?actions=%5B%5B%22G%3A%5C%5CProjects%5C%5CDigiBeat%5C%5Csrc%5C%5Capp%5C%5Cactions%5C%5Ctiktok.ts%22%2C%5B%22fetchDailyVideoBreakdown%22%2C%22fetchVideos%22%2C%22deleteAccountGroup%22%2C%22fetchSnapshots%22%2C%22upsertVideo%22%2C%22fetchAccounts%22%2C%22triggerSync%22%2C%22fetchAccountGroups%22%2C%22upsertAccount%22%2C%22updateGroupMembers%22%2C%22createAccountGroup%22%5D%5D%5D&__client_imported__=true!"
      },
      "layer": {
        "app/page": "action-browser"
      }
    }
  },
  "edge": {},
  "encryptionKey": "fHJm66UhLTfyg/FKM3lJh8Bz+mIyLU9b/5wHJoX+juw="
}